libKMCUDA-6.2.1.dist-info/WHEEL
libKMCUDA-6.2.1.dist-info/metadata.json
libKMCUDA-6.2.1.dist-info/top_level.txt
libKMCUDA-6.2.1.dist-info/DESCRIPTION.rst
libKMCUDA-6.2.1.dist-info/METADATA
libKMCUDA-6.2.1.dist-info/RECORD
libKMCUDA-6.2.1.data/purelib/libKMCUDA.so
